sonoyuncupy/__init__.py
sonoyuncupy/main.py
sonoyuncupy-0.1.dist-info/METADATA
sonoyuncupy-0.1.dist-info/WHEEL
sonoyuncupy-0.1.dist-info/top_level.txt
sonoyuncupy-0.1.dist-info/RECORD
